README
setup.py
simplefmf/__init__.py
simplefmf/simplefmf.py
simplefmf.egg-info/PKG-INFO
simplefmf.egg-info/SOURCES.txt
simplefmf.egg-info/dependency_links.txt
simplefmf.egg-info/top_level.txt
simplefmf.egg-info/zip-safe
test/test_datadefinition.py
test/test_fmftable.py
test/test_simplefmf.py