Metadata-Version: 1.1
Name: simplefmf
Version: 0.1.2
Summary: An easy way to write fmf files
Home-page: http://arxiv.org/abs/0904.1299
Author: Rolf Würdemann
Author-email: Rolf.Wuerdemann@fmf.uni-freiburg.de
License: BSD
Platform: UNKNOWN
Classifier: Development Status :: 4 - Beta
Classifier: Topic :: Utilities
Classifier: Environment :: Console
Classifier: License :: OSI Approved :: BSD License
